singlebeat/__init__.py
singlebeat/beat.py
singlebeat/cli.py
single_beat-0.6.3.dist-info/LICENSE.txt
single_beat-0.6.3.dist-info/METADATA
single_beat-0.6.3.dist-info/WHEEL
single_beat-0.6.3.dist-info/entry_points.txt
single_beat-0.6.3.dist-info/top_level.txt
single_beat-0.6.3.dist-info/zip-safe
single_beat-0.6.3.dist-info/RECORD
