Metadata-Version: 2.1
Name: single-beat
Version: 0.6.3
Summary: ensures only one instance of your process across your servers
Home-page: https://github.com/ybrs/single-beat
License: MIT
Requires-Python: >3.7.0
License-File: LICENSE.txt
Requires-Dist: redis (>=4.2.0)
Requires-Dist: Click (>=7.0)
